Workbook

Sheet Read Me
A1: Titan Company Ltd. — Financial Statement Review & Variance Analysis (FY2023–FY2025)
A3: Project 3 of 3 — Audit & Finance Skills Portfolio
A5: What this project is:
A6: A year-over-year variance and ratio analysis of Titan Company's consolidated financial results,
A7: built using live Excel formulas (not hardcoded values) to demonstrate the financial statement
A8: review and Excel skills listed in real finance/audit job postings.
A10: How to read this workbook:
A11: - Grey cells = raw input data (Titan's actual reported figures)
A12: - Blue text cells = live formulas that calculate from the grey inputs
A13: - Hover over any cell with a small red triangle to see a note explaining what it calculates
A14: - Yellow highlight = a year-over-year change exceeding 15%, flagged for investigation
A16: Tabs:
... A23: This continues from Project 1 (Internal Controls Testing), which also used Titan Company Ltd.

Sheet Variance Analysis
A1: Titan Company Ltd. — Consolidated P&L and Balance Sheet, FY2023–FY2025 (Rs. Crores)
A2: Source: Titan Company consolidated financials (Screener.in, from BSE filings). Grey = input data. Blue = live formula. Yellow = |change| > 15%.
A4: Line Item | B4: FY2023 | C4: FY2024 | D4: FY2025 | E4: FY24 vs FY23 (%) | F4: FY25 vs FY24 (%)
A5: Profit & Loss
A6: Revenue (Sales) | B6: 40575 | C6: 51084 | D6: 60456 | E6: =(C6-B6)/B6*100 -> 25.900185 | F6: =(D6-C6)/C6*100 -> 18.346253
A7: Total Expenses | B7: 35693 | C7: 45792 | D7: 54762 | E7: =(C7-B7)/B7*100 -> 28.294063 | F7: =(D7-C7)/C7*100 -> 19.588574
A8: Operating Profit | B8: 4882 | C8: 5292 | D8: 5694 | E8: =(C8-B8)/B8*100 -> 8.3981975 | F8: =(D8-C8)/C8*100 -> 7.5963719
A9: Other Income | B9: 306 | C9: 534 | D9: 487 | E9: =(C9-B9)/B9*100 -> 74.509804 | F9: =(D9-C9)/C9*100 -> -8.8014981
A10: Interest Expense | B10: 300 | C10: 619 | D10: 953 | E10: =(C10-B10)/B10*100 -> 106.33333 | F10: =(D10-C10)/C10*100 -> 53.957997
A11: Depreciation | B11: 441 | C11: 584 | D11: 693 | E11: =(C11-B11)/B11*100 -> 32.426304 | F11: =(D11-C11)/C11*100 -> 18.664384
A12: Profit Before Tax | B12: 4447 | C12: 4623 | D12: 4535 | E12: =(C12-B12)/B12*100 -> 3.9577243 | F12: =(D12-C12)/C12*100 -> -1.9035258
A13: Net Profit | B13: 3274 | C13: 3496 | D13: 3337 | E13: =(C13-B13)/B13*100 -> 6.7806964 | F13: =(D13-C13)/C13*100 -> -4.5480549
A15: Balance Sheet
A16: Reserves | B16: 11762 | C16: 9304 | D16: 11535 | E16: =(C16-B16)/B16*100 -> -20.897806 | F16: =(D16-C16)/C16*100 -> 23.978934
A17: Borrowings | B17: 9367 | C17: 15528 | D17: 20777 | E17: =(C17-B17)/B17*100 -> 65.77346 | F17: =(D17-C17)/C17*100 -> 33.803452
A18: Other Liabilities | B18: 5802 | C18: 6626 | D18: 8244 | E18: =(C18-B18)/B18*100 -> 14.201999 | F18: =(D18-C18)/C18*100 -> 24.418956
A19: Total Liabilities/Assets | B19: 27020 | C19: 31547 | D19: 40645 | E19: =(C19-B19)/B19*100 -> 16.754256 | F19: =(D19-C19)/C19*100 -> 28.839509
A20: Fixed Assets | B20: 2998 | C20: 3709 | D20: 4062 | E20: =(C20-B20)/B20*100 -> 23.715811 | F20: =(D20-C20)/C20*100 -> 9.5173901
A21: Investments | B21: 2515 | C21: 2345 | D21: 1988 | E21: =(C21-B21)/B21*100 -> -6.7594433 | F21: =(D21-C21)/C21*100 -> -15.223881
A22: Other Assets | B22: 21363 | C22: 25396 | D22: 34490 | E22: =(C22-B22)/B22*100 -> 18.878435 | F22: =(D22-C22)/C22*100 -> 35.808789

Sheet Ratio Analysis
A1: Key Ratios, FY2023–FY2025 — all calculated via formula from 'Variance Analysis' tab
A3: Ratio | B3: FY2023 | C3: FY2024 | D3: FY2025
A4: Operating Profit Margin (%) | B4: ='Variance Analysis'!B8/'Variance Analysis'!B6*100 -> 12.032039 | C4: ='Variance Analysis'!C8/'Variance Analysis'!C6*100 -> 10.359408 | D4: ='Variance Analysis'!D8/'Variance Analysis'!D6*100 -> 9.41842
A5: Net Profit Margin (%) | B5: ='Variance Analysis'!B9/'Variance Analysis'!B7*100 -> 0.85731096 | C5: ='Variance Analysis'!C9/'Variance Analysis'!C7*100 -> 1.1661426 | D5: ='Variance Analysis'!D9/'Variance Analysis'!D7*100 -> 0.8893028
A6: Debt (Borrowings) as % of Total Assets | B6: ='Variance Analysis'!B10/'Variance Analysis'!B8*100 -> 6.1450225 | C6: ='Variance Analysis'!C10/'Variance Analysis'!C8*100 -> 11.696901 | D6: ='Variance Analysis'!D10/'Variance Analysis'!D8*100 -> 16.736916
A7: Interest Coverage Ratio (x) | B7: ='Variance Analysis'!B11/'Variance Analysis'!B9*100 -> 144.11765 | C7: ='Variance Analysis'!C11/'Variance Analysis'!C9*100 -> 109.3633 | D7: ='Variance Analysis'!D11/'Variance Analysis'!D9*100 -> 142.29979
A8: Return on Equity, approx. (%) | B8: ='Variance Analysis'!B12/'Variance Analysis'!B10*100 -> 1482.3333 | C8: ='Variance Analysis'!C12/'Variance Analysis'!C10*100 -> 746.84976 | D8: ='Variance Analysis'!D12/'Variance Analysis'!D10*100 -> 475.86569
A10: Additional ratios (sourced directly from Titan's reported data, Screener.in)
A11: Debtor Days | B11: 6 | C11: 7 | D11: 6
A12: Inventory Days | B12: 199 | C12: 176 | D12: 217
A13: Days Payable | B13: 15 | C13: 13 | D13: 15
A14: Cash Conversion Cycle (days) | B14: 191 | C14: 171 | D14: 208
A15: ROCE (%) | B15: 25 | C15: 23 | D15: 19
A17: Equity-Funded % of Balance Sheet
B18: =('Variance Analysis'!B16+89)/'Variance Analysis'!B19*100 -> 43.860104 | C18: =('Variance Analysis'!C16+89)/'Variance Analysis'!C19*100 -> 29.774622 | D18: =('Variance Analysis'!D16+89)/'Variance Analysis'!D19*100 -> 28.598844

Sheet Narrative Memo
A1: Narrative Memo — Fluctuation Analysis
A3: Revenue grew strongly across both years (+25.9% FY24, +18.3% FY25), driven by Titan's jewellery
A4: business and continued store expansion. However, profitability did not keep pace: Operating
A5: Profit Margin fell from 12% to 9%, and Net Profit Margin fell even faster once rising interest
A6: costs are factored in.
A8: INVENTORY: Inventory Days rose from 176 to 217 days in FY25 (per Titan's reported ratios) —
A9: meaning gold/jewellery stock is sitting longer before being sold, tying up increasing amounts of
A10: cash. This directly confirms the inventory valuation risk identified in Project 1's Risk & Control
A11: Matrix, now visible as a real, worsening financial trend rather than a theoretical risk.
A13: FUNDING THE GROWTH: To fund this inventory buildup and broader expansion, Titan simultaneously
A14: (a) drew down its own Investments (Rs 2,515 Cr -> Rs 1,988 Cr) and (b) more than doubled its
A15: Borrowings (Rs 9,367 Cr -> Rs 20,777 Cr). As a result, the % of the balance sheet funded by
... A27: rising interest cost noted above.

Sheet Learning Notes
A1: Term | B1: Plain-English Explanation
A2: YoY Variance | B2: How much a number changed from one year to the next, shown as a percentage — the core tool for spotting unusual movements.
A3: Operating Profit Margin | B3: Operating Profit divided by Revenue — shows how much profit is made from core business operations, before interest and tax.
A4: Net Profit Margin | B4: Net Profit divided by Revenue — shows how much of every rupee of sales actually becomes final profit.
A5: Interest Coverage Ratio | B5: How many times over a company could pay its interest expense from its profits — a lower number means rising financial risk.
A6: Return on Equity (ROE) | B6: Net Profit divided by shareholders' equity — shows the return generated on the owners' own investment in the business.
A7: ROCE | B7: Return on Capital Employed — profit relative to ALL capital invested (debt + equity), not just shareholders' portion. Useful for comparing efficiency regardless of how a company is financed.
A8: Cash Conversion Cycle | B8: How many days, on average, cash is tied up between paying for inventory and collecting cash from customers. Shorter is generally healthier.
A9: Fluctuation/Variance Analysis | B9: The audit and finance practice of comparing numbers across periods and investigating any unusually large swings, rather than assuming growth is automatically good news.

Sheet Sources and Assumptions
A1: Sources and Assumptions
A3: All financial figures (Revenue, Expenses, Operating Profit, Interest, Depreciation, PBT, Net Profit,
A4: Reserves, Borrowings, Liabilities, Assets, Debtor Days, Inventory Days, Days Payable, ROCE) are
A5: Titan Company Ltd.'s actual reported CONSOLIDATED figures for FY2023, FY2024, and FY2025,
A6: sourced via Screener.in (screener.in/company/TITAN), which compiles data from Titan's official
A7: BSE filings and annual reports.
A9: This is a real company's real financial data — unlike Project 2's synthetic dataset, no figures
A10: here were invented or modified. All % changes and ratios are LIVE EXCEL FORMULAS referencing
A11: the raw input cells (grey-shaded) — not hardcoded values — so changing an input automatically
A12: recalculates every dependent figure.
A14: Equity Capital (Rs 89 Cr) is treated as constant across all 3 years for the ROE calculation,
A15: matching Titan's reported figures where Equity Capital did not change over this period.
... A18: fluctuation analysis skills, not an official or audited analysis of Titan Company.

Sheet Integrated Summary
A1: Integrated Summary — Connecting All 3 Projects
A3: Project 1 (Internal Controls Testing) flagged gold/inventory valuation as Titan's most significant
A4: audit risk area, given constant gold price volatility and the judgment involved in valuing inventory.
A6: Project 3 (this workbook) confirms this risk is materializing in real financial trends: Inventory
A7: Days rose from 176 to 217 over FY24-25, tying up increasing cash. To fund this — alongside broader
A8: growth — Titan more than doubled its borrowings and drew down its own investments, shifting from
A9: a majority equity-funded (43.9%) to a majority debt-funded (28.6%) balance sheet in two years, with
A10: Interest Coverage falling sharply as a direct consequence.
A12: Project 2 (SQL Anomaly Detection) tested the payment control environment directly and found real
A13: gaps — duplicate payments, unusual round-number transactions — meaning that at precisely the time
A14: Titan is under increasing financial pressure from its growth and inventory strategy, the basic
A15: operational controls meant to safeguard cash outflows are not yet fully effective.
... A20: while foundational payment controls still need strengthening.
